LICENSE
README.md
setup.cfg
setup.py
matrix_fact/__init__.py
matrix_fact/aa.py
matrix_fact/abnmf.py
matrix_fact/awnmf.py
matrix_fact/base.py
matrix_fact/bnmf.py
matrix_fact/chnmf.py
matrix_fact/cmde.py
matrix_fact/cmeans.py
matrix_fact/cnmf.py
matrix_fact/cur.py
matrix_fact/cursl.py
matrix_fact/dist.py
matrix_fact/greedy.py
matrix_fact/greedycur.py
matrix_fact/kmeans.py
matrix_fact/laesa.py
matrix_fact/nmf.py
matrix_fact/nndsvd.py
matrix_fact/pca.py
matrix_fact/pmf.py
matrix_fact/sivm.py
matrix_fact/sivm_cur.py
matrix_fact/sivm_gsat.py
matrix_fact/sivm_search.py
matrix_fact/sivm_sgreedy.py
matrix_fact/snmf.py
matrix_fact/svd.py
matrix_fact/torch_snmf.py
matrix_fact/wnmf.py
matrix_fact.egg-info/PKG-INFO
matrix_fact.egg-info/SOURCES.txt
matrix_fact.egg-info/dependency_links.txt
matrix_fact.egg-info/requires.txt
matrix_fact.egg-info/top_level.txt
test/test_aa.py
test/test_bnmf.py
test/test_chnmf.py
test/test_cmde.py
test/test_cmeans.py
test/test_cnmf.py
test/test_cur.py
test/test_greedy.py
test/test_greedycur.py
test/test_kmeans.py
test/test_laesa.py
test/test_nmf.py
test/test_pca.py
test/test_sivm.py
test/test_sivmcur.py
test/test_snmf.py
test/test_svd.py
test/test_torch_snmf.py
test/test_wnmf.py