Metadata-Version: 2.1
Name: matrix-fact
Version: 1.1.2
Summary: Python Matrix Factorization Module
Home-page: https://github.com/gentaiscool/matrix_fact
Author: Genta Indra Winata
Author-email: gentaindrawinata@gmail.com
License: GNU General Public License v3.0
Platform: UNKNOWN
License-File: LICENSE
